schug/__init__.py
schug/cli/__init__.py
schug/cli/base.py
schug/cli/fetch.py
schug/cli/load.py
schug/cli/serve.py
schug/config.py
schug/database/__init__.py
schug/database/genes.py
schug/database/session.py
schug/demo/__init__.py
schug/demo/exons_37.tsv
schug/demo/exons_38.tsv
schug/demo/genes_37.tsv
schug/demo/genes_38.tsv
schug/demo/transcripts_37.tsv
schug/demo/transcripts_38.tsv
schug/endpoints/__init__.py
schug/endpoints/exons.py
schug/endpoints/genes.py
schug/endpoints/http_exceptions.py
schug/endpoints/transcripts.py
schug/load/__init__.py
schug/load/biomart.py
schug/load/demo.py
schug/load/ensembl.py
schug/load/fetch_resource.py
schug/load/gene_resources.py
schug/load/omim.py
schug/main.py
schug/models/__init__.py
schug/models/common.py
schug/models/exon.py
schug/models/gene.py
schug/models/link_tables.py
schug/models/transcript.py
schug-1.13.1.dist-info/METADATA
schug-1.13.1.dist-info/WHEEL
schug-1.13.1.dist-info/entry_points.txt
schug-1.13.1.dist-info/licenses/LICENSE
schug-1.13.1.dist-info/RECORD
