Metadata-Version: 2.4
Name: schug
Version: 1.13.1
Summary: Keep track of genes, transcripts and exons from different sources
License-File: LICENSE
Author: moonso
Author-email: mans.magnusson@scilifelab.se
Requires-Python: >=3.9,<4.0
Classifier: Programming Language :: Python :: 3
Classifier: Programming Language :: Python :: 3.9
Classifier: Programming Language :: Python :: 3.10
Classifier: Programming Language :: Python :: 3.11
Classifier: Programming Language :: Python :: 3.12
Classifier: Programming Language :: Python :: 3.13
Classifier: Programming Language :: Python :: 3.14
Requires-Dist: aiofiles (>=23.1.0,<24.0.0)
Requires-Dist: certifi (==2024.07.04)
Requires-Dist: fastapi (>=0.115.2,<0.116.0)
Requires-Dist: gunicorn (==23.0.0)
Requires-Dist: httpx (>=0.23.3,<0.24.0)
Requires-Dist: importlib-resources (>=5.12.0,<6.0.0)
Requires-Dist: jinja2 (==3.1.6)
Requires-Dist: pydantic (>=2.5.2,<3.0.0)
Requires-Dist: pydantic-settings (>=2.1.0,<3.0.0)
Requires-Dist: pytest-mock (>=3.10.0,<4.0.0)
Requires-Dist: requests (>=2.28.2,<3.0.0)
Requires-Dist: setuptools (>=78.1.0,<79.0.0)
Requires-Dist: sqlmodel (>=0.0.14,<0.0.15)
Requires-Dist: starlette (==0.40.0)
Requires-Dist: typer (==0.12.3)
Requires-Dist: urllib3 (>=2.2.3,<3.0.0)
Requires-Dist: uvicorn (>=0.21.1,<0.22.0)
